LICENSE.txt
setup.cfg
setup.py
ofxReaderBR/OFXReaderBR.py
ofxReaderBR/__init__.py
ofxReaderBR.egg-info/PKG-INFO
ofxReaderBR.egg-info/SOURCES.txt
ofxReaderBR.egg-info/dependency_links.txt
ofxReaderBR.egg-info/requires.txt
ofxReaderBR.egg-info/top_level.txt
ofxReaderBR/model/__init__.py
ofxReaderBR/model/bankstatement.py
ofxReaderBR/model/cashflow.py
ofxReaderBR/model/origin.py
ofxReaderBR/model/tests.py
ofxReaderBR/reader/__init__.py
ofxReaderBR/reader/exceptions.py
ofxReaderBR/reader/factory.py
ofxReaderBR/reader/parser.py
ofxReaderBR/reader/readerbankstatement.py
ofxReaderBR/reader/readercashflow.py
ofxReaderBR/reader/readercontroller.py