Metadata-Version: 2.1
Name: ofxReaderBR
Version: 0.16.13
Summary: Convert ofx - pt_BR
Home-page: https://github.com/Fintask/ofxReaderBR/
Author: Fintask
Author-email: admin@fintask.com.br
License: MIT
Download-URL: https://github.com/Fintask/ofxReaderBR/archive/v0.16.0.tar.gz
Keywords: ofx,xlsx
Platform: UNKNOWN
Classifier: Development Status :: 3 - Alpha
Classifier: Intended Audience :: Developers
Classifier: Topic :: Software Development :: Build Tools
Classifier: License :: OSI Approved :: MIT License
Classifier: Programming Language :: Python :: 3.7
License-File: LICENSE.txt
